<?xml version="1.0" encoding="UTF-8"?>
<RetrieveValueSetResponse xmlns="urn:ihe:iti:svs:2008"
                          xmlns:xsi="http://www.w3.org/2001/XMLSchema-instance">
   <ValueSet dateFin=""
             dateMaj="20230404000000"
             dateValid="20210315000000"
             description="JDV_Sein_Localisation_tumeur_CISIS"
             displayName="JDV_Sein_Localisation_tumeur_CISIS"
             id="1.2.250.1.213.1.1.5.422"
             typeFichier="JDV"
             urlFichier="">
      <ConceptList>
         <Concept code="675"
                  codeSystem="1.3.6.1.4.1.19376.1.8.2.1"
                  displayName="Quadrant supéro-externe"/>
         <Concept code="676"
                  codeSystem="1.3.6.1.4.1.19376.1.8.2.1"
                  displayName="Quadrant inféro-externe"/>
         <Concept code="677"
                  codeSystem="1.3.6.1.4.1.19376.1.8.2.1"
                  displayName="Quadrant supéro-interne"/>
         <Concept code="678"
                  codeSystem="1.3.6.1.4.1.19376.1.8.2.1"
                  displayName="Quadrant inféro-interne"/>
         <Concept code="679"
                  codeSystem="1.3.6.1.4.1.19376.1.8.2.1"
                  displayName="Union des quadrants supérieurs"/>
         <Concept code="680"
                  codeSystem="1.3.6.1.4.1.19376.1.8.2.1"
                  displayName="Union des quadrants externes"/>
         <Concept code="681"
                  codeSystem="1.3.6.1.4.1.19376.1.8.2.1"
                  displayName="Union des quadrants internes"/>
         <Concept code="682"
                  codeSystem="1.3.6.1.4.1.19376.1.8.2.1"
                  displayName="Union des quadrants inférieurs"/>
         <Concept code="683"
                  codeSystem="1.3.6.1.4.1.19376.1.8.2.1"
                  displayName="Mamelon"/>
         <Concept code="684"
                  codeSystem="1.3.6.1.4.1.19376.1.8.2.1"
                  displayName="Central"/>
         <Concept code="685"
                  codeSystem="1.3.6.1.4.1.19376.1.8.2.1"
                  displayName="Prolongement axillaire"/>
         <Concept code="686"
                  codeSystem="1.3.6.1.4.1.19376.1.8.2.1"
                  displayName="Sillon sous-mammaire"/>
      </ConceptList>
   </ValueSet>
</RetrieveValueSetResponse>
